{
  "swagger": "2.0",
  "info": {
    "title": "My API",
    "description": "Description",
    "version": "1.0.0"
  },
  "host": "cse341-class05.onrender.com",
  "basePath": "/",
  "schemes": [
    "https"
  ],
  "paths": {
    "/api-docs": {
      "get": {
        "description": "",
        "responses": {
          "default": {
            "description": ""
          }
        }
      }
    },
    "/user/": {
      "get": {
        "description": "",
        "produces": [
          "application/json"
        ],
        "responses": {
          "200": {
            "description": "OK"
          }
        }
      },
      "post": {
        "description": "",
        "parameters": [
          {
            "name": "body",
            "in": "body",
            "schema": {
              "type": "object",
              "properties": {
                "username": {
                  "example": "any"
                },
                "password": {
                  "example": "any"
                },
                "firstname": {
                  "example": "any"
                },
                "lastname": {
                  "example": "any"
                },
                "email": {
                  "example": "any"
                },
                "phonenumber": {
                  "example": "any"
                },
                "stylename": {
                  "example": "any"
                },
                "message": {
                  "example": "any"
                }
              }
            }
          }
        ],
        "responses": {
          "201": {
            "description": "Created"
          },
          "500": {
            "description": "Internal Server Error"
          }
        }
      }
    },
    "/user/{stylename}": {
      "get": {
        "description": "",
        "produces": [
          "application/json"
        ],
        "parameters": [
          {
            "name": "stylename",
            "in": "path",
            "required": true,
            "type": "string"
          }
        ],
        "responses": {
          "200": {
            "description": "OK"
          }
        }
      }
    },
    "/painting/": {
      "get": {
        "description": "",
        "produces": [
          "application/json"
        ],
        "responses": {
          "200": {
            "description": "OK"
          }
        }
      },
      "post": {
        "description": "",
        "parameters": [
          {
            "name": "body",
            "in": "body",
            "schema": {
              "type": "object",
              "properties": {
                "painting_name": {
                  "example": "any"
                },
                "stylename": {
                  "example": "any"
                },
                "author_name": {
                  "example": "any"
                },
                "painting_description": {
                  "example": "any"
                },
                "painting_data": {
                  "example": "any"
                },
                "painting_technic": {
                  "example": "any"
                }
              }
            }
          }
        ],
        "responses": {
          "201": {
            "description": "Created"
          },
          "500": {
            "description": "Internal Server Error"
          }
        }
      }
    },
    "/painting/{stylename}": {
      "get": {
        "description": "",
        "produces": [
          "application/json"
        ],
        "parameters": [
          {
            "name": "stylename",
            "in": "path",
            "required": true,
            "type": "string"
          }
        ],
        "responses": {
          "200": {
            "description": "OK"
          }
        }
      }
    }
  }
}